{
    "students":[
        {
            "id":1,
            "first_name":"Garland",
            "last_name":"McKnockiter",
            "email":"gmcknockiter0@usgs.gov",
            "gender":"Female",
            "departmentId": 2
        },
        {
            "id":2,
            "first_name":"Weidar",
            "last_name":"McQuilty",
            "email":"wmcquilty1@archive.org",
            "gender":"Male",
            "departmentId": 2
        },
        {
            "id":3,
            "first_name":"Dew",
            "last_name":"Borrill",
            "email":"dborrill2@reuters.com",
            "gender":"Male",
            "departmentId": 1
        },
        {
            "id":4,
            "first_name":"Jeffy",
            "last_name":"Browning",
            "email":"jbrowning3@cyberchimps.com",
            "gender":"Genderfluid",
            "departmentId": 3
        },
        {
            "id":5,
            "first_name":"Bay",
            "last_name":"Ivanikov",
            "email":"bivanikov4@smh.com.au",
            "gender":"Polygender",
            "departmentId": 2
        },
        {
            "id":6,
            "first_name":"Roarke",
            "last_name":"Rankcom",
            "email":"rrankcom5@behance.net",
            "gender":"Male",
            "departmentId": 1
        },
        {
            "id":7,
            "first_name":"Adora",
            "last_name":"Zemler",
            "email":"azemler6@phpbb.com",
            "gender":"Female",
            "departmentId": 1
        },
        {
            "id":8,
            "first_name":"Cornie",
            "last_name":"Biddlecombe",
            "email":"cbiddlecombe7@vistaprint.com",
            "gender":"Genderfluid",
            "departmentId": 3
        },
        {
            "id":9,
            "first_name":"Elmer",
            "last_name":"Steart",
            "email":"esteart8@mac.com",
            "gender":"Male",
            "departmentId": 3
        },
        {
            "id":"10",
            "first_name":"Karolina",
            "last_name":"Masserel",
            "email":"kmasserel9@marketwatch.com",
            "gender":"Female",
            "departmentId": 1
        }
    ],
    "departments": [
        {
            "id": 1,
            "name": "Computer Engineering"
        },
        {
            "id": 2,
            "name": "Industrial Engineering"
        },
        {
            "id": 3,
            "name": "Mechanical Engineering"
        }
    ]
}
